tests
workfrontapi_plus
