Metadata-Version: 1.1
Name: workfrontapi-plus
Version: 1.0.23
Summary: A Python 3 compatible package for working with the Workfront API
Home-page: https://github.com/craiglathrop218/workfrontapi_plus
Author: Roshan Bal, Craig Lathrop
Author-email: none@none.com
License: MIT
Download-URL: https://github.com/craiglathrop218/workfrontapi_plus/archive/1.0.23.tar.gz
Keywords: Workfront API AtTask
Platform: UNKNOWN
Classifier: Development Status :: 5 - Production/Stable
Classifier: Intended Audience :: Developers
Classifier: License :: OSI Approved :: MIT License
Classifier: Programming Language :: Python :: 3
Classifier: Programming Language :: Python :: 3.3
Classifier: Programming Language :: Python :: 3.4
Classifier: Programming Language :: Python :: 3.5
Classifier: Programming Language :: Python :: 3.6
